whisper_mlx/__init__.py
whisper_mlx/__main__.py
whisper_mlx/audio.py
whisper_mlx/cli.py
whisper_mlx/constants.py
whisper_mlx/decoding.py
whisper_mlx/lightning.py
whisper_mlx/load_models.py
whisper_mlx/speculative.py
whisper_mlx/timing.py
whisper_mlx/tokenizer.py
whisper_mlx/transcribe.py
whisper_mlx/utils.py
whisper_mlx/whisper.py
whisper_mlx/writers.py
whisper_mlx/assets/download_assets.py
whisper_mlx/assets/gpt2.tiktoken
whisper_mlx/assets/mel_filters.npz
whisper_mlx/assets/multilingual.tiktoken
vayu_whisper-1.0.0.dist-info/METADATA
vayu_whisper-1.0.0.dist-info/WHEEL
vayu_whisper-1.0.0.dist-info/entry_points.txt
vayu_whisper-1.0.0.dist-info/top_level.txt
vayu_whisper-1.0.0.dist-info/RECORD
