Metadata-Version: 2.4
Name: vayu-whisper
Version: 1.0.0
Summary: Vayu - The fastest Whisper implementation on Apple Silicon
Author: Apple Inc., Mustafa Aljadery, Siddharth Sharma, Behnam Ebrahimi
License: MIT
Project-URL: Homepage, https://github.com/CodeWithBehnam/vayu
Project-URL: Documentation, https://github.com/CodeWithBehnam/vayu#readme
Project-URL: Repository, https://github.com/CodeWithBehnam/vayu
Keywords: vayu,whisper,speech recognition,transcription,mlx,apple silicon,machine learning,fast
Classifier: Development Status :: 4 - Beta
Classifier: Intended Audience :: Developers
Classifier: Intended Audience :: Science/Research
Classifier: License :: OSI Approved :: MIT License
Classifier: Operating System :: MacOS
Classifier: Programming Language :: Python :: 3
Classifier: Programming Language :: Python :: 3.10
Classifier: Programming Language :: Python :: 3.11
Classifier: Programming Language :: Python :: 3.12
Classifier: Topic :: Scientific/Engineering :: Artificial Intelligence
Classifier: Topic :: Multimedia :: Sound/Audio :: Speech
Requires-Python: >=3.10
Requires-Dist: mlx>=0.11
Requires-Dist: numpy
Requires-Dist: tqdm
Requires-Dist: tiktoken
Requires-Dist: huggingface_hub
Requires-Dist: numba
Requires-Dist: scipy
Provides-Extra: dev
Requires-Dist: pytest; extra == "dev"
Requires-Dist: black; extra == "dev"
Requires-Dist: isort; extra == "dev"
Requires-Dist: mypy; extra == "dev"
Provides-Extra: notebook
Requires-Dist: ipykernel; extra == "notebook"
Requires-Dist: jupyter; extra == "notebook"
